patrol/__init__.py
patrol/__main__.py
patrol/cli.py
patrol/config.py
patrol/patrol.py
patrol/utils.py
patrol/sentry_api_client/__init__.py
patrol/sentry_api_client/api.py
patrol/sentry_api_client/resource.py
sentry_patrol-1.0.0.dist-info/LICENSE
sentry_patrol-1.0.0.dist-info/METADATA
sentry_patrol-1.0.0.dist-info/WHEEL
sentry_patrol-1.0.0.dist-info/entry_points.txt
sentry_patrol-1.0.0.dist-info/top_level.txt
sentry_patrol-1.0.0.dist-info/RECORD
