Metadata-Version: 2.1
Name: sentry-patrol
Version: 1.0.0
Summary: Command Line program to interact with sentry API
Home-page: https://github.com/daneoshiga/sentry-patrol
Author: Danilo Shiga
Author-email: daniloshiga@gmail.com
License: MIT
Keywords: sentry cli patrol
Platform: UNKNOWN
Classifier: Development Status :: 4 - Beta
Classifier: Environment :: Console
Classifier: Intended Audience :: Developers
Classifier: License :: OSI Approved :: MIT License
Classifier: Natural Language :: English
Classifier: Operating System :: OS Independent
Classifier: Programming Language :: Python :: 3 :: Only
Classifier: Programming Language :: Python :: 3.6
Classifier: Programming Language :: Python :: 3.7
Classifier: Topic :: System :: Distributed Computing
Requires-Dist: click (<6.8,>=6.7)
Requires-Dist: prettyconf
Requires-Dist: simple-rest-client (>=1.0.0)
